pyimageexport/__init__.py
pyimageexport-1.0.0.dist-info/LICENSE
pyimageexport-1.0.0.dist-info/METADATA
pyimageexport-1.0.0.dist-info/WHEEL
pyimageexport-1.0.0.dist-info/top_level.txt
pyimageexport-1.0.0.dist-info/RECORD
