Metadata-Version: 2.1
Name: pyimageexport
Version: 1.0.0
Summary: Package to convert various formats of raster graphics images in a single line of code
Home-page: https://gitlab.com/azael_rguez/py-image-export
Author: Alvaro Azael Rodriguez Rodriguez
Author-email: azael.rguez96@gmail.com
License: MIT
Platform: UNKNOWN
Classifier: Programming Language :: Python :: 3
Classifier: License :: OSI Approved :: MIT License
Classifier: Operating System :: OS Independent
Requires-Python: >=3.6
Requires-Dist: Pillow
